{"nodes": [{"id": "e_computes_project_openenv_src_openenv_core_containers_runtime_providers_py", "label": "providers.py", "file_type": "code", "source_file": "E:\\COMPUTES\\PROJECT\\OpenEnv\\src\\openenv\\core\\containers\\runtime\\providers.py", "source_location": "L1"}, {"id": "providers_containerprovider", "label": "ContainerProvider", "file_type": "code", "source_file": "E:\\COMPUTES\\PROJECT\\OpenEnv\\src\\openenv\\core\\containers\\runtime\\providers.py", "source_location": "L20"}, {"id": "abc", "label": "ABC", "file_type": "code", "source_file": "", "source_location": ""}, {"id": "providers_start_container", "label": "start_container()", "file_type": "code", "source_file": "E:\\COMPUTES\\PROJECT\\OpenEnv\\src\\openenv\\core\\containers\\runtime\\providers.py", "source_location": "L42"}, {"id": "providers_stop_container", "label": "stop_container()", "file_type": "code", "source_file": "E:\\COMPUTES\\PROJECT\\OpenEnv\\src\\openenv\\core\\containers\\runtime\\providers.py", "source_location": "L67"}, {"id": "providers_wait_for_ready", "label": "wait_for_ready()", "file_type": "code", "source_file": "E:\\COMPUTES\\PROJECT\\OpenEnv\\src\\openenv\\core\\containers\\runtime\\providers.py", "source_location": "L76"}, {"id": "providers_localdockerprovider", "label": "LocalDockerProvider", "file_type": "code", "source_file": "E:\\COMPUTES\\PROJECT\\OpenEnv\\src\\openenv\\core\\containers\\runtime\\providers.py", "source_location": "L92"}, {"id": "providers_localdockerprovider_init", "label": ".__init__()", "file_type": "code", "source_file": "E:\\COMPUTES\\PROJECT\\OpenEnv\\src\\openenv\\core\\containers\\runtime\\providers.py", "source_location": "L106"}, {"id": "providers_localdockerprovider_start_container", "label": ".start_container()", "file_type": "code", "source_file": "E:\\COMPUTES\\PROJECT\\OpenEnv\\src\\openenv\\core\\containers\\runtime\\providers.py", "source_location": "L130"}, {"id": "providers_localdockerprovider_stop_container", "label": ".stop_container()", "file_type": "code", "source_file": "E:\\COMPUTES\\PROJECT\\OpenEnv\\src\\openenv\\core\\containers\\runtime\\providers.py", "source_location": "L192"}, {"id": "providers_localdockerprovider_wait_for_ready", "label": ".wait_for_ready()", "file_type": "code", "source_file": "E:\\COMPUTES\\PROJECT\\OpenEnv\\src\\openenv\\core\\containers\\runtime\\providers.py", "source_location": "L224"}, {"id": "providers_localdockerprovider_find_available_port", "label": "._find_available_port()", "file_type": "code", "source_file": "E:\\COMPUTES\\PROJECT\\OpenEnv\\src\\openenv\\core\\containers\\runtime\\providers.py", "source_location": "L259"}, {"id": "providers_localdockerprovider_generate_container_name", "label": "._generate_container_name()", "file_type": "code", "source_file": "E:\\COMPUTES\\PROJECT\\OpenEnv\\src\\openenv\\core\\containers\\runtime\\providers.py", "source_location": "L274"}, {"id": "providers_dockerswarmprovider", "label": "DockerSwarmProvider", "file_type": "code", "source_file": "E:\\COMPUTES\\PROJECT\\OpenEnv\\src\\openenv\\core\\containers\\runtime\\providers.py", "source_location": "L291"}, {"id": "providers_dockerswarmprovider_init", "label": ".__init__()", "file_type": "code", "source_file": "E:\\COMPUTES\\PROJECT\\OpenEnv\\src\\openenv\\core\\containers\\runtime\\providers.py", "source_location": "L301"}, {"id": "providers_dockerswarmprovider_start_container", "label": ".start_container()", "file_type": "code", "source_file": "E:\\COMPUTES\\PROJECT\\OpenEnv\\src\\openenv\\core\\containers\\runtime\\providers.py", "source_location": "L327"}, {"id": "providers_dockerswarmprovider_stop_container", "label": ".stop_container()", "file_type": "code", "source_file": "E:\\COMPUTES\\PROJECT\\OpenEnv\\src\\openenv\\core\\containers\\runtime\\providers.py", "source_location": "L439"}, {"id": "providers_dockerswarmprovider_wait_for_ready", "label": ".wait_for_ready()", "file_type": "code", "source_file": "E:\\COMPUTES\\PROJECT\\OpenEnv\\src\\openenv\\core\\containers\\runtime\\providers.py", "source_location": "L463"}, {"id": "providers_dockerswarmprovider_ensure_docker_available", "label": "._ensure_docker_available()", "file_type": "code", "source_file": "E:\\COMPUTES\\PROJECT\\OpenEnv\\src\\openenv\\core\\containers\\runtime\\providers.py", "source_location": "L495"}, {"id": "providers_dockerswarmprovider_ensure_swarm_initialized", "label": "._ensure_swarm_initialized()", "file_type": "code", "source_file": "E:\\COMPUTES\\PROJECT\\OpenEnv\\src\\openenv\\core\\containers\\runtime\\providers.py", "source_location": "L514"}, {"id": "providers_dockerswarmprovider_ensure_overlay_network", "label": "._ensure_overlay_network()", "file_type": "code", "source_file": "E:\\COMPUTES\\PROJECT\\OpenEnv\\src\\openenv\\core\\containers\\runtime\\providers.py", "source_location": "L546"}, {"id": "providers_dockerswarmprovider_find_available_port", "label": "._find_available_port()", "file_type": "code", "source_file": "E:\\COMPUTES\\PROJECT\\OpenEnv\\src\\openenv\\core\\containers\\runtime\\providers.py", "source_location": "L576"}, {"id": "providers_dockerswarmprovider_generate_service_name", "label": "._generate_service_name()", "file_type": "code", "source_file": "E:\\COMPUTES\\PROJECT\\OpenEnv\\src\\openenv\\core\\containers\\runtime\\providers.py", "source_location": "L585"}, {"id": "providers_kubernetesprovider", "label": "KubernetesProvider", "file_type": "code", "source_file": "E:\\COMPUTES\\PROJECT\\OpenEnv\\src\\openenv\\core\\containers\\runtime\\providers.py", "source_location": "L593"}, {"id": "providers_runtimeprovider", "label": "RuntimeProvider", "file_type": "code", "source_file": "E:\\COMPUTES\\PROJECT\\OpenEnv\\src\\openenv\\core\\containers\\runtime\\providers.py", "source_location": "L610"}, {"id": "providers_start", "label": "start()", "file_type": "code", "source_file": "E:\\COMPUTES\\PROJECT\\OpenEnv\\src\\openenv\\core\\containers\\runtime\\providers.py", "source_location": "L627"}, {"id": "providers_stop", "label": "stop()", "file_type": "code", "source_file": "E:\\COMPUTES\\PROJECT\\OpenEnv\\src\\openenv\\core\\containers\\runtime\\providers.py", "source_location": "L644"}, {"id": "providers_runtimeprovider_enter", "label": ".__enter__()", "file_type": "code", "source_file": "E:\\COMPUTES\\PROJECT\\OpenEnv\\src\\openenv\\core\\containers\\runtime\\providers.py", "source_location": "L657"}, {"id": "providers_runtimeprovider_exit", "label": ".__exit__()", "file_type": "code", "source_file": "E:\\COMPUTES\\PROJECT\\OpenEnv\\src\\openenv\\core\\containers\\runtime\\providers.py", "source_location": "L664"}, {"id": "providers_rationale_21", "label": "Abstract base class for container providers.      Providers implement this inter", "file_type": "rationale", "source_file": "E:\\COMPUTES\\PROJECT\\OpenEnv\\src\\openenv\\core\\containers\\runtime\\providers.py", "source_location": "L21"}, {"id": "providers_rationale_49", "label": "Start a container from the specified image.          Args:             image: Co", "file_type": "rationale", "source_file": "E:\\COMPUTES\\PROJECT\\OpenEnv\\src\\openenv\\core\\containers\\runtime\\providers.py", "source_location": "L49"}, {"id": "providers_rationale_68", "label": "Stop and remove the running container.          This cleans up the container tha", "file_type": "rationale", "source_file": "E:\\COMPUTES\\PROJECT\\OpenEnv\\src\\openenv\\core\\containers\\runtime\\providers.py", "source_location": "L68"}, {"id": "providers_rationale_77", "label": "Wait for the container to be ready to accept requests.          This typically p", "file_type": "rationale", "source_file": "E:\\COMPUTES\\PROJECT\\OpenEnv\\src\\openenv\\core\\containers\\runtime\\providers.py", "source_location": "L77"}, {"id": "providers_rationale_93", "label": "Container provider for local Docker daemon.      This provider runs containers o", "file_type": "rationale", "source_file": "E:\\COMPUTES\\PROJECT\\OpenEnv\\src\\openenv\\core\\containers\\runtime\\providers.py", "source_location": "L93"}, {"id": "providers_rationale_107", "label": "Initialize the local Docker provider.", "file_type": "rationale", "source_file": "E:\\COMPUTES\\PROJECT\\OpenEnv\\src\\openenv\\core\\containers\\runtime\\providers.py", "source_location": "L107"}, {"id": "providers_rationale_137", "label": "Start a Docker container locally.          Args:             image: Docker image", "file_type": "rationale", "source_file": "E:\\COMPUTES\\PROJECT\\OpenEnv\\src\\openenv\\core\\containers\\runtime\\providers.py", "source_location": "L137"}, {"id": "providers_rationale_193", "label": "Stop and remove the Docker container.", "file_type": "rationale", "source_file": "E:\\COMPUTES\\PROJECT\\OpenEnv\\src\\openenv\\core\\containers\\runtime\\providers.py", "source_location": "L193"}, {"id": "providers_rationale_225", "label": "Wait for container to be ready by polling /health endpoint.          Args:", "file_type": "rationale", "source_file": "E:\\COMPUTES\\PROJECT\\OpenEnv\\src\\openenv\\core\\containers\\runtime\\providers.py", "source_location": "L225"}, {"id": "providers_rationale_260", "label": "Find an available port on localhost.          Returns:             An available", "file_type": "rationale", "source_file": "E:\\COMPUTES\\PROJECT\\OpenEnv\\src\\openenv\\core\\containers\\runtime\\providers.py", "source_location": "L260"}, {"id": "providers_rationale_275", "label": "Generate a unique container name based on image name and timestamp.          Arg", "file_type": "rationale", "source_file": "E:\\COMPUTES\\PROJECT\\OpenEnv\\src\\openenv\\core\\containers\\runtime\\providers.py", "source_location": "L275"}, {"id": "providers_rationale_292", "label": "Container provider that uses Docker Swarm services for local concurrency.      T", "file_type": "rationale", "source_file": "E:\\COMPUTES\\PROJECT\\OpenEnv\\src\\openenv\\core\\containers\\runtime\\providers.py", "source_location": "L292"}, {"id": "providers_rationale_307", "label": "Args:             auto_init_swarm: Whether to call ``docker swarm init`` when Sw", "file_type": "rationale", "source_file": "E:\\COMPUTES\\PROJECT\\OpenEnv\\src\\openenv\\core\\containers\\runtime\\providers.py", "source_location": "L307"}, {"id": "providers_rationale_334", "label": "Start (or scale) a Swarm service for the given image.          Supported kwargs:", "file_type": "rationale", "source_file": "E:\\COMPUTES\\PROJECT\\OpenEnv\\src\\openenv\\core\\containers\\runtime\\providers.py", "source_location": "L334"}, {"id": "providers_rationale_440", "label": "Remove the Swarm service (and keep the Swarm manager running).", "file_type": "rationale", "source_file": "E:\\COMPUTES\\PROJECT\\OpenEnv\\src\\openenv\\core\\containers\\runtime\\providers.py", "source_location": "L440"}, {"id": "providers_rationale_464", "label": "Wait for at least one replica to become healthy by polling /health.          Not", "file_type": "rationale", "source_file": "E:\\COMPUTES\\PROJECT\\OpenEnv\\src\\openenv\\core\\containers\\runtime\\providers.py", "source_location": "L464"}, {"id": "providers_rationale_594", "label": "Container provider for Kubernetes clusters.      This provider creates pods in a", "file_type": "rationale", "source_file": "E:\\COMPUTES\\PROJECT\\OpenEnv\\src\\openenv\\core\\containers\\runtime\\providers.py", "source_location": "L594"}, {"id": "providers_rationale_611", "label": "Abstract base class for runtime providers that are not container providers.", "file_type": "rationale", "source_file": "E:\\COMPUTES\\PROJECT\\OpenEnv\\src\\openenv\\core\\containers\\runtime\\providers.py", "source_location": "L611"}, {"id": "providers_rationale_633", "label": "Start a runtime from the specified image.          Args:             image: Runt", "file_type": "rationale", "source_file": "E:\\COMPUTES\\PROJECT\\OpenEnv\\src\\openenv\\core\\containers\\runtime\\providers.py", "source_location": "L633"}, {"id": "providers_rationale_652", "label": "Wait for the runtime to be ready to accept requests.", "file_type": "rationale", "source_file": "E:\\COMPUTES\\PROJECT\\OpenEnv\\src\\openenv\\core\\containers\\runtime\\providers.py", "source_location": "L652"}, {"id": "providers_rationale_658", "label": "Enter the runtime provider.", "file_type": "rationale", "source_file": "E:\\COMPUTES\\PROJECT\\OpenEnv\\src\\openenv\\core\\containers\\runtime\\providers.py", "source_location": "L658"}, {"id": "providers_rationale_665", "label": "Exit the runtime provider.", "file_type": "rationale", "source_file": "E:\\COMPUTES\\PROJECT\\OpenEnv\\src\\openenv\\core\\containers\\runtime\\providers.py", "source_location": "L665"}], "edges": [{"source": "e_computes_project_openenv_src_openenv_core_containers_runtime_providers_py", "target": "abc", "relation": "imports_from", "confidence": "EXTRACTED", "source_file": "E:\\COMPUTES\\PROJECT\\OpenEnv\\src\\openenv\\core\\containers\\runtime\\providers.py", "source_location": "L16", "weight": 1.0}, {"source": "e_computes_project_openenv_src_openenv_core_containers_runtime_providers_py", "target": "typing", "relation": "imports_from", "confidence": "EXTRACTED", "source_file": "E:\\COMPUTES\\PROJECT\\OpenEnv\\src\\openenv\\core\\containers\\runtime\\providers.py", "source_location": "L17", "weight": 1.0}, {"source": "e_computes_project_openenv_src_openenv_core_containers_runtime_providers_py", "target": "providers_containerprovider", "relation": "contains", "confidence": "EXTRACTED", "source_file": "E:\\COMPUTES\\PROJECT\\OpenEnv\\src\\openenv\\core\\containers\\runtime\\providers.py", "source_location": "L20", "weight": 1.0}, {"source": "providers_containerprovider", "target": "abc", "relation": "inherits", "confidence": "EXTRACTED", "source_file": "E:\\COMPUTES\\PROJECT\\OpenEnv\\src\\openenv\\core\\containers\\runtime\\providers.py", "source_location": "L20", "weight": 1.0}, {"source": "e_computes_project_openenv_src_openenv_core_containers_runtime_providers_py", "target": "providers_start_container", "relation": "contains", "confidence": "EXTRACTED", "source_file": "E:\\COMPUTES\\PROJECT\\OpenEnv\\src\\openenv\\core\\containers\\runtime\\providers.py", "source_location": "L42", "weight": 1.0}, {"source": "e_computes_project_openenv_src_openenv_core_containers_runtime_providers_py", "target": "providers_stop_container", "relation": "contains", "confidence": "EXTRACTED", "source_file": "E:\\COMPUTES\\PROJECT\\OpenEnv\\src\\openenv\\core\\containers\\runtime\\providers.py", "source_location": "L67", "weight": 1.0}, {"source": "e_computes_project_openenv_src_openenv_core_containers_runtime_providers_py", "target": "providers_wait_for_ready", "relation": "contains", "confidence": "EXTRACTED", "source_file": "E:\\COMPUTES\\PROJECT\\OpenEnv\\src\\openenv\\core\\containers\\runtime\\providers.py", "source_location": "L76", "weight": 1.0}, {"source": "e_computes_project_openenv_src_openenv_core_containers_runtime_providers_py", "target": "providers_localdockerprovider", "relation": "contains", "confidence": "EXTRACTED", "source_file": "E:\\COMPUTES\\PROJECT\\OpenEnv\\src\\openenv\\core\\containers\\runtime\\providers.py", "source_location": "L92", "weight": 1.0}, {"source": "providers_localdockerprovider", "target": "providers_containerprovider", "relation": "inherits", "confidence": "EXTRACTED", "source_file": "E:\\COMPUTES\\PROJECT\\OpenEnv\\src\\openenv\\core\\containers\\runtime\\providers.py", "source_location": "L92", "weight": 1.0}, {"source": "providers_localdockerprovider", "target": "providers_localdockerprovider_init", "relation": "method", "confidence": "EXTRACTED", "source_file": "E:\\COMPUTES\\PROJECT\\OpenEnv\\src\\openenv\\core\\containers\\runtime\\providers.py", "source_location": "L106", "weight": 1.0}, {"source": "providers_localdockerprovider", "target": "providers_localdockerprovider_start_container", "relation": "method", "confidence": "EXTRACTED", "source_file": "E:\\COMPUTES\\PROJECT\\OpenEnv\\src\\openenv\\core\\containers\\runtime\\providers.py", "source_location": "L130", "weight": 1.0}, {"source": "providers_localdockerprovider", "target": "providers_localdockerprovider_stop_container", "relation": "method", "confidence": "EXTRACTED", "source_file": "E:\\COMPUTES\\PROJECT\\OpenEnv\\src\\openenv\\core\\containers\\runtime\\providers.py", "source_location": "L192", "weight": 1.0}, {"source": "providers_localdockerprovider", "target": "providers_localdockerprovider_wait_for_ready", "relation": "method", "confidence": "EXTRACTED", "source_file": "E:\\COMPUTES\\PROJECT\\OpenEnv\\src\\openenv\\core\\containers\\runtime\\providers.py", "source_location": "L224", "weight": 1.0}, {"source": "providers_localdockerprovider", "target": "providers_localdockerprovider_find_available_port", "relation": "method", "confidence": "EXTRACTED", "source_file": "E:\\COMPUTES\\PROJECT\\OpenEnv\\src\\openenv\\core\\containers\\runtime\\providers.py", "source_location": "L259", "weight": 1.0}, {"source": "providers_localdockerprovider", "target": "providers_localdockerprovider_generate_container_name", "relation": "method", "confidence": "EXTRACTED", "source_file": "E:\\COMPUTES\\PROJECT\\OpenEnv\\src\\openenv\\core\\containers\\runtime\\providers.py", "source_location": "L274", "weight": 1.0}, {"source": "e_computes_project_openenv_src_openenv_core_containers_runtime_providers_py", "target": "providers_dockerswarmprovider", "relation": "contains", "confidence": "EXTRACTED", "source_file": "E:\\COMPUTES\\PROJECT\\OpenEnv\\src\\openenv\\core\\containers\\runtime\\providers.py", "source_location": "L291", "weight": 1.0}, {"source": "providers_dockerswarmprovider", "target": "providers_containerprovider", "relation": "inherits", "confidence": "EXTRACTED", "source_file": "E:\\COMPUTES\\PROJECT\\OpenEnv\\src\\openenv\\core\\containers\\runtime\\providers.py", "source_location": "L291", "weight": 1.0}, {"source": "providers_dockerswarmprovider", "target": "providers_dockerswarmprovider_init", "relation": "method", "confidence": "EXTRACTED", "source_file": "E:\\COMPUTES\\PROJECT\\OpenEnv\\src\\openenv\\core\\containers\\runtime\\providers.py", "source_location": "L301", "weight": 1.0}, {"source": "providers_dockerswarmprovider", "target": "providers_dockerswarmprovider_start_container", "relation": "method", "confidence": "EXTRACTED", "source_file": "E:\\COMPUTES\\PROJECT\\OpenEnv\\src\\openenv\\core\\containers\\runtime\\providers.py", "source_location": "L327", "weight": 1.0}, {"source": "providers_dockerswarmprovider", "target": "providers_dockerswarmprovider_stop_container", "relation": "method", "confidence": "EXTRACTED", "source_file": "E:\\COMPUTES\\PROJECT\\OpenEnv\\src\\openenv\\core\\containers\\runtime\\providers.py", "source_location": "L439", "weight": 1.0}, {"source": "providers_dockerswarmprovider", "target": "providers_dockerswarmprovider_wait_for_ready", "relation": "method", "confidence": "EXTRACTED", "source_file": "E:\\COMPUTES\\PROJECT\\OpenEnv\\src\\openenv\\core\\containers\\runtime\\providers.py", "source_location": "L463", "weight": 1.0}, {"source": "providers_dockerswarmprovider", "target": "providers_dockerswarmprovider_ensure_docker_available", "relation": "method", "confidence": "EXTRACTED", "source_file": "E:\\COMPUTES\\PROJECT\\OpenEnv\\src\\openenv\\core\\containers\\runtime\\providers.py", "source_location": "L495", "weight": 1.0}, {"source": "providers_dockerswarmprovider", "target": "providers_dockerswarmprovider_ensure_swarm_initialized", "relation": "method", "confidence": "EXTRACTED", "source_file": "E:\\COMPUTES\\PROJECT\\OpenEnv\\src\\openenv\\core\\containers\\runtime\\providers.py", "source_location": "L514", "weight": 1.0}, {"source": "providers_dockerswarmprovider", "target": "providers_dockerswarmprovider_ensure_overlay_network", "relation": "method", "confidence": "EXTRACTED", "source_file": "E:\\COMPUTES\\PROJECT\\OpenEnv\\src\\openenv\\core\\containers\\runtime\\providers.py", "source_location": "L546", "weight": 1.0}, {"source": "providers_dockerswarmprovider", "target": "providers_dockerswarmprovider_find_available_port", "relation": "method", "confidence": "EXTRACTED", "source_file": "E:\\COMPUTES\\PROJECT\\OpenEnv\\src\\openenv\\core\\containers\\runtime\\providers.py", "source_location": "L576", "weight": 1.0}, {"source": "providers_dockerswarmprovider", "target": "providers_dockerswarmprovider_generate_service_name", "relation": "method", "confidence": "EXTRACTED", "source_file": "E:\\COMPUTES\\PROJECT\\OpenEnv\\src\\openenv\\core\\containers\\runtime\\providers.py", "source_location": "L585", "weight": 1.0}, {"source": "e_computes_project_openenv_src_openenv_core_containers_runtime_providers_py", "target": "providers_kubernetesprovider", "relation": "contains", "confidence": "EXTRACTED", "source_file": "E:\\COMPUTES\\PROJECT\\OpenEnv\\src\\openenv\\core\\containers\\runtime\\providers.py", "source_location": "L593", "weight": 1.0}, {"source": "providers_kubernetesprovider", "target": "providers_containerprovider", "relation": "inherits", "confidence": "EXTRACTED", "source_file": "E:\\COMPUTES\\PROJECT\\OpenEnv\\src\\openenv\\core\\containers\\runtime\\providers.py", "source_location": "L593", "weight": 1.0}, {"source": "e_computes_project_openenv_src_openenv_core_containers_runtime_providers_py", "target": "providers_runtimeprovider", "relation": "contains", "confidence": "EXTRACTED", "source_file": "E:\\COMPUTES\\PROJECT\\OpenEnv\\src\\openenv\\core\\containers\\runtime\\providers.py", "source_location": "L610", "weight": 1.0}, {"source": "providers_runtimeprovider", "target": "abc", "relation": "inherits", "confidence": "EXTRACTED", "source_file": "E:\\COMPUTES\\PROJECT\\OpenEnv\\src\\openenv\\core\\containers\\runtime\\providers.py", "source_location": "L610", "weight": 1.0}, {"source": "e_computes_project_openenv_src_openenv_core_containers_runtime_providers_py", "target": "providers_start", "relation": "contains", "confidence": "EXTRACTED", "source_file": "E:\\COMPUTES\\PROJECT\\OpenEnv\\src\\openenv\\core\\containers\\runtime\\providers.py", "source_location": "L627", "weight": 1.0}, {"source": "e_computes_project_openenv_src_openenv_core_containers_runtime_providers_py", "target": "providers_stop", "relation": "contains", "confidence": "EXTRACTED", "source_file": "E:\\COMPUTES\\PROJECT\\OpenEnv\\src\\openenv\\core\\containers\\runtime\\providers.py", "source_location": "L644", "weight": 1.0}, {"source": "e_computes_project_openenv_src_openenv_core_containers_runtime_providers_py", "target": "providers_wait_for_ready", "relation": "contains", "confidence": "EXTRACTED", "source_file": "E:\\COMPUTES\\PROJECT\\OpenEnv\\src\\openenv\\core\\containers\\runtime\\providers.py", "source_location": "L651", "weight": 1.0}, {"source": "providers_runtimeprovider", "target": "providers_runtimeprovider_enter", "relation": "method", "confidence": "EXTRACTED", "source_file": "E:\\COMPUTES\\PROJECT\\OpenEnv\\src\\openenv\\core\\containers\\runtime\\providers.py", "source_location": "L657", "weight": 1.0}, {"source": "providers_runtimeprovider", "target": "providers_runtimeprovider_exit", "relation": "method", "confidence": "EXTRACTED", "source_file": "E:\\COMPUTES\\PROJECT\\OpenEnv\\src\\openenv\\core\\containers\\runtime\\providers.py", "source_location": "L664", "weight": 1.0}, {"source": "providers_localdockerprovider_start_container", "target": "providers_dockerswarmprovider_find_available_port", "relation": "calls", "confidence": "EXTRACTED", "source_file": "E:\\COMPUTES\\PROJECT\\OpenEnv\\src\\openenv\\core\\containers\\runtime\\providers.py", "source_location": "L154", "weight": 1.0}, {"source": "providers_localdockerprovider_start_container", "target": "providers_localdockerprovider_generate_container_name", "relation": "calls", "confidence": "EXTRACTED", "source_file": "E:\\COMPUTES\\PROJECT\\OpenEnv\\src\\openenv\\core\\containers\\runtime\\providers.py", "source_location": "L157", "weight": 1.0}, {"source": "providers_dockerswarmprovider_init", "target": "providers_dockerswarmprovider_ensure_docker_available", "relation": "calls", "confidence": "EXTRACTED", "source_file": "E:\\COMPUTES\\PROJECT\\OpenEnv\\src\\openenv\\core\\containers\\runtime\\providers.py", "source_location": "L322", "weight": 1.0}, {"source": "providers_dockerswarmprovider_init", "target": "providers_dockerswarmprovider_ensure_swarm_initialized", "relation": "calls", "confidence": "EXTRACTED", "source_file": "E:\\COMPUTES\\PROJECT\\OpenEnv\\src\\openenv\\core\\containers\\runtime\\providers.py", "source_location": "L323", "weight": 1.0}, {"source": "providers_dockerswarmprovider_init", "target": "providers_dockerswarmprovider_ensure_overlay_network", "relation": "calls", "confidence": "EXTRACTED", "source_file": "E:\\COMPUTES\\PROJECT\\OpenEnv\\src\\openenv\\core\\containers\\runtime\\providers.py", "source_location": "L325", "weight": 1.0}, {"source": "providers_dockerswarmprovider_start_container", "target": "providers_dockerswarmprovider_find_available_port", "relation": "calls", "confidence": "EXTRACTED", "source_file": "E:\\COMPUTES\\PROJECT\\OpenEnv\\src\\openenv\\core\\containers\\runtime\\providers.py", "source_location": "L369", "weight": 1.0}, {"source": "providers_dockerswarmprovider_start_container", "target": "providers_dockerswarmprovider_generate_service_name", "relation": "calls", "confidence": "EXTRACTED", "source_file": "E:\\COMPUTES\\PROJECT\\OpenEnv\\src\\openenv\\core\\containers\\runtime\\providers.py", "source_location": "L371", "weight": 1.0}, {"source": "providers_runtimeprovider_enter", "target": "providers_start", "relation": "calls", "confidence": "EXTRACTED", "source_file": "E:\\COMPUTES\\PROJECT\\OpenEnv\\src\\openenv\\core\\containers\\runtime\\providers.py", "source_location": "L661", "weight": 1.0}, {"source": "providers_runtimeprovider_exit", "target": "providers_stop", "relation": "calls", "confidence": "EXTRACTED", "source_file": "E:\\COMPUTES\\PROJECT\\OpenEnv\\src\\openenv\\core\\containers\\runtime\\providers.py", "source_location": "L668", "weight": 1.0}, {"source": "providers_rationale_21", "target": "providers_containerprovider", "relation": "rationale_for", "confidence": "EXTRACTED", "source_file": "E:\\COMPUTES\\PROJECT\\OpenEnv\\src\\openenv\\core\\containers\\runtime\\providers.py", "source_location": "L21", "weight": 1.0}, {"source": "providers_rationale_49", "target": "providers_containerprovider_start_container", "relation": "rationale_for", "confidence": "EXTRACTED", "source_file": "E:\\COMPUTES\\PROJECT\\OpenEnv\\src\\openenv\\core\\containers\\runtime\\providers.py", "source_location": "L49", "weight": 1.0}, {"source": "providers_rationale_68", "target": "providers_containerprovider_stop_container", "relation": "rationale_for", "confidence": "EXTRACTED", "source_file": "E:\\COMPUTES\\PROJECT\\OpenEnv\\src\\openenv\\core\\containers\\runtime\\providers.py", "source_location": "L68", "weight": 1.0}, {"source": "providers_rationale_77", "target": "providers_containerprovider_wait_for_ready", "relation": "rationale_for", "confidence": "EXTRACTED", "source_file": "E:\\COMPUTES\\PROJECT\\OpenEnv\\src\\openenv\\core\\containers\\runtime\\providers.py", "source_location": "L77", "weight": 1.0}, {"source": "providers_rationale_93", "target": "providers_localdockerprovider", "relation": "rationale_for", "confidence": "EXTRACTED", "source_file": "E:\\COMPUTES\\PROJECT\\OpenEnv\\src\\openenv\\core\\containers\\runtime\\providers.py", "source_location": "L93", "weight": 1.0}, {"source": "providers_rationale_107", "target": "providers_localdockerprovider_init", "relation": "rationale_for", "confidence": "EXTRACTED", "source_file": "E:\\COMPUTES\\PROJECT\\OpenEnv\\src\\openenv\\core\\containers\\runtime\\providers.py", "source_location": "L107", "weight": 1.0}, {"source": "providers_rationale_137", "target": "providers_localdockerprovider_start_container", "relation": "rationale_for", "confidence": "EXTRACTED", "source_file": "E:\\COMPUTES\\PROJECT\\OpenEnv\\src\\openenv\\core\\containers\\runtime\\providers.py", "source_location": "L137", "weight": 1.0}, {"source": "providers_rationale_193", "target": "providers_localdockerprovider_stop_container", "relation": "rationale_for", "confidence": "EXTRACTED", "source_file": "E:\\COMPUTES\\PROJECT\\OpenEnv\\src\\openenv\\core\\containers\\runtime\\providers.py", "source_location": "L193", "weight": 1.0}, {"source": "providers_rationale_225", "target": "providers_localdockerprovider_wait_for_ready", "relation": "rationale_for", "confidence": "EXTRACTED", "source_file": "E:\\COMPUTES\\PROJECT\\OpenEnv\\src\\openenv\\core\\containers\\runtime\\providers.py", "source_location": "L225", "weight": 1.0}, {"source": "providers_rationale_260", "target": "providers_localdockerprovider_find_available_port", "relation": "rationale_for", "confidence": "EXTRACTED", "source_file": "E:\\COMPUTES\\PROJECT\\OpenEnv\\src\\openenv\\core\\containers\\runtime\\providers.py", "source_location": "L260", "weight": 1.0}, {"source": "providers_rationale_275", "target": "providers_localdockerprovider_generate_container_name", "relation": "rationale_for", "confidence": "EXTRACTED", "source_file": "E:\\COMPUTES\\PROJECT\\OpenEnv\\src\\openenv\\core\\containers\\runtime\\providers.py", "source_location": "L275", "weight": 1.0}, {"source": "providers_rationale_292", "target": "providers_dockerswarmprovider", "relation": "rationale_for", "confidence": "EXTRACTED", "source_file": "E:\\COMPUTES\\PROJECT\\OpenEnv\\src\\openenv\\core\\containers\\runtime\\providers.py", "source_location": "L292", "weight": 1.0}, {"source": "providers_rationale_307", "target": "providers_dockerswarmprovider_init", "relation": "rationale_for", "confidence": "EXTRACTED", "source_file": "E:\\COMPUTES\\PROJECT\\OpenEnv\\src\\openenv\\core\\containers\\runtime\\providers.py", "source_location": "L307", "weight": 1.0}, {"source": "providers_rationale_334", "target": "providers_dockerswarmprovider_start_container", "relation": "rationale_for", "confidence": "EXTRACTED", "source_file": "E:\\COMPUTES\\PROJECT\\OpenEnv\\src\\openenv\\core\\containers\\runtime\\providers.py", "source_location": "L334", "weight": 1.0}, {"source": "providers_rationale_440", "target": "providers_dockerswarmprovider_stop_container", "relation": "rationale_for", "confidence": "EXTRACTED", "source_file": "E:\\COMPUTES\\PROJECT\\OpenEnv\\src\\openenv\\core\\containers\\runtime\\providers.py", "source_location": "L440", "weight": 1.0}, {"source": "providers_rationale_464", "target": "providers_dockerswarmprovider_wait_for_ready", "relation": "rationale_for", "confidence": "EXTRACTED", "source_file": "E:\\COMPUTES\\PROJECT\\OpenEnv\\src\\openenv\\core\\containers\\runtime\\providers.py", "source_location": "L464", "weight": 1.0}, {"source": "providers_rationale_594", "target": "providers_kubernetesprovider", "relation": "rationale_for", "confidence": "EXTRACTED", "source_file": "E:\\COMPUTES\\PROJECT\\OpenEnv\\src\\openenv\\core\\containers\\runtime\\providers.py", "source_location": "L594", "weight": 1.0}, {"source": "providers_rationale_611", "target": "providers_runtimeprovider", "relation": "rationale_for", "confidence": "EXTRACTED", "source_file": "E:\\COMPUTES\\PROJECT\\OpenEnv\\src\\openenv\\core\\containers\\runtime\\providers.py", "source_location": "L611", "weight": 1.0}, {"source": "providers_rationale_633", "target": "providers_runtimeprovider_start", "relation": "rationale_for", "confidence": "EXTRACTED", "source_file": "E:\\COMPUTES\\PROJECT\\OpenEnv\\src\\openenv\\core\\containers\\runtime\\providers.py", "source_location": "L633", "weight": 1.0}, {"source": "providers_rationale_652", "target": "providers_runtimeprovider_wait_for_ready", "relation": "rationale_for", "confidence": "EXTRACTED", "source_file": "E:\\COMPUTES\\PROJECT\\OpenEnv\\src\\openenv\\core\\containers\\runtime\\providers.py", "source_location": "L652", "weight": 1.0}, {"source": "providers_rationale_658", "target": "providers_runtimeprovider_enter", "relation": "rationale_for", "confidence": "EXTRACTED", "source_file": "E:\\COMPUTES\\PROJECT\\OpenEnv\\src\\openenv\\core\\containers\\runtime\\providers.py", "source_location": "L658", "weight": 1.0}, {"source": "providers_rationale_665", "target": "providers_runtimeprovider_exit", "relation": "rationale_for", "confidence": "EXTRACTED", "source_file": "E:\\COMPUTES\\PROJECT\\OpenEnv\\src\\openenv\\core\\containers\\runtime\\providers.py", "source_location": "L665", "weight": 1.0}], "raw_calls": [{"caller_nid": "providers_localdockerprovider_init", "callee": "run", "source_file": "E:\\COMPUTES\\PROJECT\\OpenEnv\\src\\openenv\\core\\containers\\runtime\\providers.py", "source_location": "L115"}, {"caller_nid": "providers_localdockerprovider_init", "callee": "RuntimeError", "source_file": "E:\\COMPUTES\\PROJECT\\OpenEnv\\src\\openenv\\core\\containers\\runtime\\providers.py", "source_location": "L126"}, {"caller_nid": "providers_localdockerprovider_start_container", "callee": "items", "source_file": "E:\\COMPUTES\\PROJECT\\OpenEnv\\src\\openenv\\core\\containers\\runtime\\providers.py", "source_location": "L172"}, {"caller_nid": "providers_localdockerprovider_start_container", "callee": "extend", "source_file": "E:\\COMPUTES\\PROJECT\\OpenEnv\\src\\openenv\\core\\containers\\runtime\\providers.py", "source_location": "L173"}, {"caller_nid": "providers_localdockerprovider_start_container", "callee": "append", "source_file": "E:\\COMPUTES\\PROJECT\\OpenEnv\\src\\openenv\\core\\containers\\runtime\\providers.py", "source_location": "L176"}, {"caller_nid": "providers_localdockerprovider_start_container", "callee": "run", "source_file": "E:\\COMPUTES\\PROJECT\\OpenEnv\\src\\openenv\\core\\containers\\runtime\\providers.py", "source_location": "L180"}, {"caller_nid": "providers_localdockerprovider_start_container", "callee": "strip", "source_file": "E:\\COMPUTES\\PROJECT\\OpenEnv\\src\\openenv\\core\\containers\\runtime\\providers.py", "source_location": "L181"}, {"caller_nid": "providers_localdockerprovider_start_container", "callee": "join", "source_file": "E:\\COMPUTES\\PROJECT\\OpenEnv\\src\\openenv\\core\\containers\\runtime\\providers.py", "source_location": "L183"}, {"caller_nid": "providers_localdockerprovider_start_container", "callee": "RuntimeError", "source_file": "E:\\COMPUTES\\PROJECT\\OpenEnv\\src\\openenv\\core\\containers\\runtime\\providers.py", "source_location": "L184"}, {"caller_nid": "providers_localdockerprovider_start_container", "callee": "sleep", "source_file": "E:\\COMPUTES\\PROJECT\\OpenEnv\\src\\openenv\\core\\containers\\runtime\\providers.py", "source_location": "L187"}, {"caller_nid": "providers_localdockerprovider_stop_container", "callee": "run", "source_file": "E:\\COMPUTES\\PROJECT\\OpenEnv\\src\\openenv\\core\\containers\\runtime\\providers.py", "source_location": "L203"}, {"caller_nid": "providers_localdockerprovider_stop_container", "callee": "run", "source_file": "E:\\COMPUTES\\PROJECT\\OpenEnv\\src\\openenv\\core\\containers\\runtime\\providers.py", "source_location": "L211"}, {"caller_nid": "providers_localdockerprovider_wait_for_ready", "callee": "time", "source_file": "E:\\COMPUTES\\PROJECT\\OpenEnv\\src\\openenv\\core\\containers\\runtime\\providers.py", "source_location": "L239"}, {"caller_nid": "providers_localdockerprovider_wait_for_ready", "callee": "time", "source_file": "E:\\COMPUTES\\PROJECT\\OpenEnv\\src\\openenv\\core\\containers\\runtime\\providers.py", "source_location": "L245"}, {"caller_nid": "providers_localdockerprovider_wait_for_ready", "callee": "get", "source_file": "E:\\COMPUTES\\PROJECT\\OpenEnv\\src\\openenv\\core\\containers\\runtime\\providers.py", "source_location": "L247"}, {"caller_nid": "providers_localdockerprovider_wait_for_ready", "callee": "sleep", "source_file": "E:\\COMPUTES\\PROJECT\\OpenEnv\\src\\openenv\\core\\containers\\runtime\\providers.py", "source_location": "L253"}, {"caller_nid": "providers_localdockerprovider_wait_for_ready", "callee": "TimeoutError", "source_file": "E:\\COMPUTES\\PROJECT\\OpenEnv\\src\\openenv\\core\\containers\\runtime\\providers.py", "source_location": "L255"}, {"caller_nid": "providers_localdockerprovider_find_available_port", "callee": "socket", "source_file": "E:\\COMPUTES\\PROJECT\\OpenEnv\\src\\openenv\\core\\containers\\runtime\\providers.py", "source_location": "L268"}, {"caller_nid": "providers_localdockerprovider_find_available_port", "callee": "bind", "source_file": "E:\\COMPUTES\\PROJECT\\OpenEnv\\src\\openenv\\core\\containers\\runtime\\providers.py", "source_location": "L269"}, {"caller_nid": "providers_localdockerprovider_find_available_port", "callee": "listen", "source_file": "E:\\COMPUTES\\PROJECT\\OpenEnv\\src\\openenv\\core\\containers\\runtime\\providers.py", "source_location": "L270"}, {"caller_nid": "providers_localdockerprovider_find_available_port", "callee": "getsockname", "source_file": "E:\\COMPUTES\\PROJECT\\OpenEnv\\src\\openenv\\core\\containers\\runtime\\providers.py", "source_location": "L271"}, {"caller_nid": "providers_localdockerprovider_generate_container_name", "callee": "split", "source_file": "E:\\COMPUTES\\PROJECT\\OpenEnv\\src\\openenv\\core\\containers\\runtime\\providers.py", "source_location": "L286"}, {"caller_nid": "providers_localdockerprovider_generate_container_name", "callee": "split", "source_file": "E:\\COMPUTES\\PROJECT\\OpenEnv\\src\\openenv\\core\\containers\\runtime\\providers.py", "source_location": "L286"}, {"caller_nid": "providers_localdockerprovider_generate_container_name", "callee": "int", "source_file": "E:\\COMPUTES\\PROJECT\\OpenEnv\\src\\openenv\\core\\containers\\runtime\\providers.py", "source_location": "L287"}, {"caller_nid": "providers_localdockerprovider_generate_container_name", "callee": "time", "source_file": "E:\\COMPUTES\\PROJECT\\OpenEnv\\src\\openenv\\core\\containers\\runtime\\providers.py", "source_location": "L287"}, {"caller_nid": "providers_dockerswarmprovider_start_container", "callee": "set", "source_file": "E:\\COMPUTES\\PROJECT\\OpenEnv\\src\\openenv\\core\\containers\\runtime\\providers.py", "source_location": "L357"}, {"caller_nid": "providers_dockerswarmprovider_start_container", "callee": "ValueError", "source_file": "E:\\COMPUTES\\PROJECT\\OpenEnv\\src\\openenv\\core\\containers\\runtime\\providers.py", "source_location": "L359"}, {"caller_nid": "providers_dockerswarmprovider_start_container", "callee": "int", "source_file": "E:\\COMPUTES\\PROJECT\\OpenEnv\\src\\openenv\\core\\containers\\runtime\\providers.py", "source_location": "L361"}, {"caller_nid": "providers_dockerswarmprovider_start_container", "callee": "get", "source_file": "E:\\COMPUTES\\PROJECT\\OpenEnv\\src\\openenv\\core\\containers\\runtime\\providers.py", "source_location": "L361"}, {"caller_nid": "providers_dockerswarmprovider_start_container", "callee": "get", "source_file": "E:\\COMPUTES\\PROJECT\\OpenEnv\\src\\openenv\\core\\containers\\runtime\\providers.py", "source_location": "L362"}, {"caller_nid": "providers_dockerswarmprovider_start_container", "callee": "get", "source_file": "E:\\COMPUTES\\PROJECT\\OpenEnv\\src\\openenv\\core\\containers\\runtime\\providers.py", "source_location": "L363"}, {"caller_nid": "providers_dockerswarmprovider_start_container", "callee": "get", "source_file": "E:\\COMPUTES\\PROJECT\\OpenEnv\\src\\openenv\\core\\containers\\runtime\\providers.py", "source_location": "L364"}, {"caller_nid": "providers_dockerswarmprovider_start_container", "callee": "get", "source_file": "E:\\COMPUTES\\PROJECT\\OpenEnv\\src\\openenv\\core\\containers\\runtime\\providers.py", "source_location": "L365"}, {"caller_nid": "providers_dockerswarmprovider_start_container", "callee": "get", "source_file": "E:\\COMPUTES\\PROJECT\\OpenEnv\\src\\openenv\\core\\containers\\runtime\\providers.py", "source_location": "L366"}, {"caller_nid": "providers_dockerswarmprovider_start_container", "callee": "str", "source_file": "E:\\COMPUTES\\PROJECT\\OpenEnv\\src\\openenv\\core\\containers\\runtime\\providers.py", "source_location": "L382"}, {"caller_nid": "providers_dockerswarmprovider_start_container", "callee": "max", "source_file": "E:\\COMPUTES\\PROJECT\\OpenEnv\\src\\openenv\\core\\containers\\runtime\\providers.py", "source_location": "L382"}, {"caller_nid": "providers_dockerswarmprovider_start_container", "callee": "extend", "source_file": "E:\\COMPUTES\\PROJECT\\OpenEnv\\src\\openenv\\core\\containers\\runtime\\providers.py", "source_location": "L388"}, {"caller_nid": "providers_dockerswarmprovider_start_container", "callee": "items", "source_file": "E:\\COMPUTES\\PROJECT\\OpenEnv\\src\\openenv\\core\\containers\\runtime\\providers.py", "source_location": "L391"}, {"caller_nid": "providers_dockerswarmprovider_start_container", "callee": "extend", "source_file": "E:\\COMPUTES\\PROJECT\\OpenEnv\\src\\openenv\\core\\containers\\runtime\\providers.py", "source_location": "L392"}, {"caller_nid": "providers_dockerswarmprovider_start_container", "callee": "extend", "source_file": "E:\\COMPUTES\\PROJECT\\OpenEnv\\src\\openenv\\core\\containers\\runtime\\providers.py", "source_location": "L395"}, {"caller_nid": "providers_dockerswarmprovider_start_container", "callee": "str", "source_file": "E:\\COMPUTES\\PROJECT\\OpenEnv\\src\\openenv\\core\\containers\\runtime\\providers.py", "source_location": "L395"}, {"caller_nid": "providers_dockerswarmprovider_start_container", "callee": "extend", "source_file": "E:\\COMPUTES\\PROJECT\\OpenEnv\\src\\openenv\\core\\containers\\runtime\\providers.py", "source_location": "L398"}, {"caller_nid": "providers_dockerswarmprovider_start_container", "callee": "str", "source_file": "E:\\COMPUTES\\PROJECT\\OpenEnv\\src\\openenv\\core\\containers\\runtime\\providers.py", "source_location": "L398"}, {"caller_nid": "providers_dockerswarmprovider_start_container", "callee": "extend", "source_file": "E:\\COMPUTES\\PROJECT\\OpenEnv\\src\\openenv\\core\\containers\\runtime\\providers.py", "source_location": "L402"}, {"caller_nid": "providers_dockerswarmprovider_start_container", "callee": "items", "source_file": "E:\\COMPUTES\\PROJECT\\OpenEnv\\src\\openenv\\core\\containers\\runtime\\providers.py", "source_location": "L405"}, {"caller_nid": "providers_dockerswarmprovider_start_container", "callee": "extend", "source_file": "E:\\COMPUTES\\PROJECT\\OpenEnv\\src\\openenv\\core\\containers\\runtime\\providers.py", "source_location": "L406"}, {"caller_nid": "providers_dockerswarmprovider_start_container", "callee": "append", "source_file": "E:\\COMPUTES\\PROJECT\\OpenEnv\\src\\openenv\\core\\containers\\runtime\\providers.py", "source_location": "L408"}, {"caller_nid": "providers_dockerswarmprovider_start_container", "callee": "isinstance", "source_file": "E:\\COMPUTES\\PROJECT\\OpenEnv\\src\\openenv\\core\\containers\\runtime\\providers.py", "source_location": "L411"}, {"caller_nid": "providers_dockerswarmprovider_start_container", "callee": "extend", "source_file": "E:\\COMPUTES\\PROJECT\\OpenEnv\\src\\openenv\\core\\containers\\runtime\\providers.py", "source_location": "L412"}, {"caller_nid": "providers_dockerswarmprovider_start_container", "callee": "split", "source_file": "E:\\COMPUTES\\PROJECT\\OpenEnv\\src\\openenv\\core\\containers\\runtime\\providers.py", "source_location": "L412"}, {"caller_nid": "providers_dockerswarmprovider_start_container", "callee": "extend", "source_file": "E:\\COMPUTES\\PROJECT\\OpenEnv\\src\\openenv\\core\\containers\\runtime\\providers.py", "source_location": "L414"}, {"caller_nid": "providers_dockerswarmprovider_start_container", "callee": "run", "source_file": "E:\\COMPUTES\\PROJECT\\OpenEnv\\src\\openenv\\core\\containers\\runtime\\providers.py", "source_location": "L417"}, {"caller_nid": "providers_dockerswarmprovider_start_container", "callee": "strip", "source_file": "E:\\COMPUTES\\PROJECT\\OpenEnv\\src\\openenv\\core\\containers\\runtime\\providers.py", "source_location": "L423"}, {"caller_nid": "providers_dockerswarmprovider_start_container", "callee": "join", "source_file": "E:\\COMPUTES\\PROJECT\\OpenEnv\\src\\openenv\\core\\containers\\runtime\\providers.py", "source_location": "L427"}, {"caller_nid": "providers_dockerswarmprovider_start_container", "callee": "RuntimeError", "source_file": "E:\\COMPUTES\\PROJECT\\OpenEnv\\src\\openenv\\core\\containers\\runtime\\providers.py", "source_location": "L432"}, {"caller_nid": "providers_dockerswarmprovider_start_container", "callee": "sleep", "source_file": "E:\\COMPUTES\\PROJECT\\OpenEnv\\src\\openenv\\core\\containers\\runtime\\providers.py", "source_location": "L435"}, {"caller_nid": "providers_dockerswarmprovider_stop_container", "callee": "run", "source_file": "E:\\COMPUTES\\PROJECT\\OpenEnv\\src\\openenv\\core\\containers\\runtime\\providers.py", "source_location": "L449"}, {"caller_nid": "providers_dockerswarmprovider_wait_for_ready", "callee": "time", "source_file": "E:\\COMPUTES\\PROJECT\\OpenEnv\\src\\openenv\\core\\containers\\runtime\\providers.py", "source_location": "L475"}, {"caller_nid": "providers_dockerswarmprovider_wait_for_ready", "callee": "time", "source_file": "E:\\COMPUTES\\PROJECT\\OpenEnv\\src\\openenv\\core\\containers\\runtime\\providers.py", "source_location": "L481"}, {"caller_nid": "providers_dockerswarmprovider_wait_for_ready", "callee": "get", "source_file": "E:\\COMPUTES\\PROJECT\\OpenEnv\\src\\openenv\\core\\containers\\runtime\\providers.py", "source_location": "L483"}, {"caller_nid": "providers_dockerswarmprovider_wait_for_ready", "callee": "sleep", "source_file": "E:\\COMPUTES\\PROJECT\\OpenEnv\\src\\openenv\\core\\containers\\runtime\\providers.py", "source_location": "L489"}, {"caller_nid": "providers_dockerswarmprovider_wait_for_ready", "callee": "TimeoutError", "source_file": "E:\\COMPUTES\\PROJECT\\OpenEnv\\src\\openenv\\core\\containers\\runtime\\providers.py", "source_location": "L491"}, {"caller_nid": "providers_dockerswarmprovider_ensure_docker_available", "callee": "run", "source_file": "E:\\COMPUTES\\PROJECT\\OpenEnv\\src\\openenv\\core\\containers\\runtime\\providers.py", "source_location": "L499"}, {"caller_nid": "providers_dockerswarmprovider_ensure_docker_available", "callee": "RuntimeError", "source_file": "E:\\COMPUTES\\PROJECT\\OpenEnv\\src\\openenv\\core\\containers\\runtime\\providers.py", "source_location": "L510"}, {"caller_nid": "providers_dockerswarmprovider_ensure_swarm_initialized", "callee": "run", "source_file": "E:\\COMPUTES\\PROJECT\\OpenEnv\\src\\openenv\\core\\containers\\runtime\\providers.py", "source_location": "L518"}, {"caller_nid": "providers_dockerswarmprovider_ensure_swarm_initialized", "callee": "lower", "source_file": "E:\\COMPUTES\\PROJECT\\OpenEnv\\src\\openenv\\core\\containers\\runtime\\providers.py", "source_location": "L525"}, {"caller_nid": "providers_dockerswarmprovider_ensure_swarm_initialized", "callee": "strip", "source_file": "E:\\COMPUTES\\PROJECT\\OpenEnv\\src\\openenv\\core\\containers\\runtime\\providers.py", "source_location": "L525"}, {"caller_nid": "providers_dockerswarmprovider_ensure_swarm_initialized", "callee": "RuntimeError", "source_file": "E:\\COMPUTES\\PROJECT\\OpenEnv\\src\\openenv\\core\\containers\\runtime\\providers.py", "source_location": "L532"}, {"caller_nid": "providers_dockerswarmprovider_ensure_swarm_initialized", "callee": "run", "source_file": "E:\\COMPUTES\\PROJECT\\OpenEnv\\src\\openenv\\core\\containers\\runtime\\providers.py", "source_location": "L537"}, {"caller_nid": "providers_dockerswarmprovider_ensure_swarm_initialized", "callee": "RuntimeError", "source_file": "E:\\COMPUTES\\PROJECT\\OpenEnv\\src\\openenv\\core\\containers\\runtime\\providers.py", "source_location": "L544"}, {"caller_nid": "providers_dockerswarmprovider_ensure_overlay_network", "callee": "run", "source_file": "E:\\COMPUTES\\PROJECT\\OpenEnv\\src\\openenv\\core\\containers\\runtime\\providers.py", "source_location": "L549"}, {"caller_nid": "providers_dockerswarmprovider_ensure_overlay_network", "callee": "run", "source_file": "E:\\COMPUTES\\PROJECT\\OpenEnv\\src\\openenv\\core\\containers\\runtime\\providers.py", "source_location": "L559"}, {"caller_nid": "providers_dockerswarmprovider_ensure_overlay_network", "callee": "RuntimeError", "source_file": "E:\\COMPUTES\\PROJECT\\OpenEnv\\src\\openenv\\core\\containers\\runtime\\providers.py", "source_location": "L574"}, {"caller_nid": "providers_dockerswarmprovider_find_available_port", "callee": "socket", "source_file": "E:\\COMPUTES\\PROJECT\\OpenEnv\\src\\openenv\\core\\containers\\runtime\\providers.py", "source_location": "L579"}, {"caller_nid": "providers_dockerswarmprovider_find_available_port", "callee": "bind", "source_file": "E:\\COMPUTES\\PROJECT\\OpenEnv\\src\\openenv\\core\\containers\\runtime\\providers.py", "source_location": "L580"}, {"caller_nid": "providers_dockerswarmprovider_find_available_port", "callee": "listen", "source_file": "E:\\COMPUTES\\PROJECT\\OpenEnv\\src\\openenv\\core\\containers\\runtime\\providers.py", "source_location": "L581"}, {"caller_nid": "providers_dockerswarmprovider_find_available_port", "callee": "getsockname", "source_file": "E:\\COMPUTES\\PROJECT\\OpenEnv\\src\\openenv\\core\\containers\\runtime\\providers.py", "source_location": "L582"}, {"caller_nid": "providers_dockerswarmprovider_generate_service_name", "callee": "split", "source_file": "E:\\COMPUTES\\PROJECT\\OpenEnv\\src\\openenv\\core\\containers\\runtime\\providers.py", "source_location": "L588"}, {"caller_nid": "providers_dockerswarmprovider_generate_service_name", "callee": "split", "source_file": "E:\\COMPUTES\\PROJECT\\OpenEnv\\src\\openenv\\core\\containers\\runtime\\providers.py", "source_location": "L588"}, {"caller_nid": "providers_dockerswarmprovider_generate_service_name", "callee": "int", "source_file": "E:\\COMPUTES\\PROJECT\\OpenEnv\\src\\openenv\\core\\containers\\runtime\\providers.py", "source_location": "L589"}, {"caller_nid": "providers_dockerswarmprovider_generate_service_name", "callee": "time", "source_file": "E:\\COMPUTES\\PROJECT\\OpenEnv\\src\\openenv\\core\\containers\\runtime\\providers.py", "source_location": "L589"}]}