{"nodes": [{"id": "e_computes_project_openenv_envs_kernrl_problems_level7_4_crosscorrelation_2d_py", "label": "4_CrossCorrelation_2D.py", "file_type": "code", "source_file": "E:\\COMPUTES\\PROJECT\\OpenEnv\\envs\\kernrl\\problems\\level7\\4_CrossCorrelation_2D.py", "source_location": "L1"}, {"id": "4_crosscorrelation_2d_model", "label": "Model", "file_type": "code", "source_file": "E:\\COMPUTES\\PROJECT\\OpenEnv\\envs\\kernrl\\problems\\level7\\4_CrossCorrelation_2D.py", "source_location": "L19"}, {"id": "4_crosscorrelation_2d_model_init", "label": ".__init__()", "file_type": "code", "source_file": "E:\\COMPUTES\\PROJECT\\OpenEnv\\envs\\kernrl\\problems\\level7\\4_CrossCorrelation_2D.py", "source_location": "L24"}, {"id": "4_crosscorrelation_2d_model_forward", "label": ".forward()", "file_type": "code", "source_file": "E:\\COMPUTES\\PROJECT\\OpenEnv\\envs\\kernrl\\problems\\level7\\4_CrossCorrelation_2D.py", "source_location": "L33"}, {"id": "4_crosscorrelation_2d_get_inputs", "label": "get_inputs()", "file_type": "code", "source_file": "E:\\COMPUTES\\PROJECT\\OpenEnv\\envs\\kernrl\\problems\\level7\\4_CrossCorrelation_2D.py", "source_location": "L60"}, {"id": "4_crosscorrelation_2d_get_init_inputs", "label": "get_init_inputs()", "file_type": "code", "source_file": "E:\\COMPUTES\\PROJECT\\OpenEnv\\envs\\kernrl\\problems\\level7\\4_CrossCorrelation_2D.py", "source_location": "L65"}, {"id": "4_crosscorrelation_2d_rationale_1", "label": "2D Cross-Correlation (Template Matching)  Slides a template over an image and co", "file_type": "rationale", "source_file": "E:\\COMPUTES\\PROJECT\\OpenEnv\\envs\\kernrl\\problems\\level7\\4_CrossCorrelation_2D.py", "source_location": "L1"}, {"id": "4_crosscorrelation_2d_rationale_20", "label": "2D cross-correlation for template matching.", "file_type": "rationale", "source_file": "E:\\COMPUTES\\PROJECT\\OpenEnv\\envs\\kernrl\\problems\\level7\\4_CrossCorrelation_2D.py", "source_location": "L20"}, {"id": "4_crosscorrelation_2d_rationale_34", "label": "Compute cross-correlation between image and template.          Args:", "file_type": "rationale", "source_file": "E:\\COMPUTES\\PROJECT\\OpenEnv\\envs\\kernrl\\problems\\level7\\4_CrossCorrelation_2D.py", "source_location": "L34"}], "edges": [{"source": "e_computes_project_openenv_envs_kernrl_problems_level7_4_crosscorrelation_2d_py", "target": "torch", "relation": "imports", "confidence": "EXTRACTED", "source_file": "E:\\COMPUTES\\PROJECT\\OpenEnv\\envs\\kernrl\\problems\\level7\\4_CrossCorrelation_2D.py", "source_location": "L14", "weight": 1.0}, {"source": "e_computes_project_openenv_envs_kernrl_problems_level7_4_crosscorrelation_2d_py", "target": "torch_nn", "relation": "imports", "confidence": "EXTRACTED", "source_file": "E:\\COMPUTES\\PROJECT\\OpenEnv\\envs\\kernrl\\problems\\level7\\4_CrossCorrelation_2D.py", "source_location": "L15", "weight": 1.0}, {"source": "e_computes_project_openenv_envs_kernrl_problems_level7_4_crosscorrelation_2d_py", "target": "torch_nn_functional", "relation": "imports", "confidence": "EXTRACTED", "source_file": "E:\\COMPUTES\\PROJECT\\OpenEnv\\envs\\kernrl\\problems\\level7\\4_CrossCorrelation_2D.py", "source_location": "L16", "weight": 1.0}, {"source": "e_computes_project_openenv_envs_kernrl_problems_level7_4_crosscorrelation_2d_py", "target": "4_crosscorrelation_2d_model", "relation": "contains", "confidence": "EXTRACTED", "source_file": "E:\\COMPUTES\\PROJECT\\OpenEnv\\envs\\kernrl\\problems\\level7\\4_CrossCorrelation_2D.py", "source_location": "L19", "weight": 1.0}, {"source": "4_crosscorrelation_2d_model", "target": "4_crosscorrelation_2d_model_init", "relation": "method", "confidence": "EXTRACTED", "source_file": "E:\\COMPUTES\\PROJECT\\OpenEnv\\envs\\kernrl\\problems\\level7\\4_CrossCorrelation_2D.py", "source_location": "L24", "weight": 1.0}, {"source": "4_crosscorrelation_2d_model", "target": "4_crosscorrelation_2d_model_forward", "relation": "method", "confidence": "EXTRACTED", "source_file": "E:\\COMPUTES\\PROJECT\\OpenEnv\\envs\\kernrl\\problems\\level7\\4_CrossCorrelation_2D.py", "source_location": "L33", "weight": 1.0}, {"source": "e_computes_project_openenv_envs_kernrl_problems_level7_4_crosscorrelation_2d_py", "target": "4_crosscorrelation_2d_get_inputs", "relation": "contains", "confidence": "EXTRACTED", "source_file": "E:\\COMPUTES\\PROJECT\\OpenEnv\\envs\\kernrl\\problems\\level7\\4_CrossCorrelation_2D.py", "source_location": "L60", "weight": 1.0}, {"source": "e_computes_project_openenv_envs_kernrl_problems_level7_4_crosscorrelation_2d_py", "target": "4_crosscorrelation_2d_get_init_inputs", "relation": "contains", "confidence": "EXTRACTED", "source_file": "E:\\COMPUTES\\PROJECT\\OpenEnv\\envs\\kernrl\\problems\\level7\\4_CrossCorrelation_2D.py", "source_location": "L65", "weight": 1.0}, {"source": "4_crosscorrelation_2d_rationale_1", "target": "e_computes_project_openenv_envs_kernrl_problems_level7_4_crosscorrelation_2d_py", "relation": "rationale_for", "confidence": "EXTRACTED", "source_file": "E:\\COMPUTES\\PROJECT\\OpenEnv\\envs\\kernrl\\problems\\level7\\4_CrossCorrelation_2D.py", "source_location": "L1", "weight": 1.0}, {"source": "4_crosscorrelation_2d_rationale_20", "target": "4_crosscorrelation_2d_model", "relation": "rationale_for", "confidence": "EXTRACTED", "source_file": "E:\\COMPUTES\\PROJECT\\OpenEnv\\envs\\kernrl\\problems\\level7\\4_CrossCorrelation_2D.py", "source_location": "L20", "weight": 1.0}, {"source": "4_crosscorrelation_2d_rationale_34", "target": "4_crosscorrelation_2d_model_forward", "relation": "rationale_for", "confidence": "EXTRACTED", "source_file": "E:\\COMPUTES\\PROJECT\\OpenEnv\\envs\\kernrl\\problems\\level7\\4_CrossCorrelation_2D.py", "source_location": "L34", "weight": 1.0}], "raw_calls": [{"caller_nid": "4_crosscorrelation_2d_model_init", "callee": "super", "source_file": "E:\\COMPUTES\\PROJECT\\OpenEnv\\envs\\kernrl\\problems\\level7\\4_CrossCorrelation_2D.py", "source_location": "L25"}, {"caller_nid": "4_crosscorrelation_2d_model_init", "callee": "randn", "source_file": "E:\\COMPUTES\\PROJECT\\OpenEnv\\envs\\kernrl\\problems\\level7\\4_CrossCorrelation_2D.py", "source_location": "L30"}, {"caller_nid": "4_crosscorrelation_2d_model_init", "callee": "register_buffer", "source_file": "E:\\COMPUTES\\PROJECT\\OpenEnv\\envs\\kernrl\\problems\\level7\\4_CrossCorrelation_2D.py", "source_location": "L31"}, {"caller_nid": "4_crosscorrelation_2d_model_forward", "callee": "unsqueeze", "source_file": "E:\\COMPUTES\\PROJECT\\OpenEnv\\envs\\kernrl\\problems\\level7\\4_CrossCorrelation_2D.py", "source_location": "L43"}, {"caller_nid": "4_crosscorrelation_2d_model_forward", "callee": "unsqueeze", "source_file": "E:\\COMPUTES\\PROJECT\\OpenEnv\\envs\\kernrl\\problems\\level7\\4_CrossCorrelation_2D.py", "source_location": "L43"}, {"caller_nid": "4_crosscorrelation_2d_model_forward", "callee": "conv2d", "source_file": "E:\\COMPUTES\\PROJECT\\OpenEnv\\envs\\kernrl\\problems\\level7\\4_CrossCorrelation_2D.py", "source_location": "L50"}, {"caller_nid": "4_crosscorrelation_2d_model_forward", "callee": "squeeze", "source_file": "E:\\COMPUTES\\PROJECT\\OpenEnv\\envs\\kernrl\\problems\\level7\\4_CrossCorrelation_2D.py", "source_location": "L52"}, {"caller_nid": "4_crosscorrelation_2d_model_forward", "callee": "squeeze", "source_file": "E:\\COMPUTES\\PROJECT\\OpenEnv\\envs\\kernrl\\problems\\level7\\4_CrossCorrelation_2D.py", "source_location": "L52"}, {"caller_nid": "4_crosscorrelation_2d_get_inputs", "callee": "randn", "source_file": "E:\\COMPUTES\\PROJECT\\OpenEnv\\envs\\kernrl\\problems\\level7\\4_CrossCorrelation_2D.py", "source_location": "L61"}]}